{
  "setName": "Code of the Duelist Sneak Peek Participation Card",
  "rarities": {
    "secret": [],
    "ultra": [
      {
        "id": 67267333,
        "name": "Vendread Houndhorde",
        "card_images": [
          {
            "id": 67267333,
            "image_url": "https://images.ygoprodeck.com/images/cards/67267333.jpg",
            "image_url_small": "https://images.ygoprodeck.com/images/cards_small/67267333.jpg",
            "image_url_cropped": "https://images.ygoprodeck.com/images/cards_cropped/67267333.jpg"
          }
        ]
      }
    ],
    "super": [],
    "rare": [],
    "common": []
  }
}