{
  "setName": "OTS Tournament Pack 25",
  "rarities": {
    "secret": [],
    "ultra": [],
    "super": [
      {
        "id": 73898890,
        "name": "Dyna Mondo",
        "card_images": [
          {
            "id": 73898890,
            "image_url": "https://images.ygoprodeck.com/images/cards/73898890.jpg",
            "image_url_small": "https://images.ygoprodeck.com/images/cards_small/73898890.jpg",
            "image_url_cropped": "https://images.ygoprodeck.com/images/cards_cropped/73898890.jpg"
          }
        ]
      },
      {
        "id": 18621798,
        "name": "Fire King Avatar Arvata",
        "card_images": [
          {
            "id": 18621798,
            "image_url": "https://images.ygoprodeck.com/images/cards/18621798.jpg",
            "image_url_small": "https://images.ygoprodeck.com/images/cards_small/18621798.jpg",
            "image_url_cropped": "https://images.ygoprodeck.com/images/cards_cropped/18621798.jpg"
          }
        ]
      },
      {
        "id": 57554544,
        "name": "Fire King Island",
        "card_images": [
          {
            "id": 57554544,
            "image_url": "https://images.ygoprodeck.com/images/cards/57554544.jpg",
            "image_url_small": "https://images.ygoprodeck.com/images/cards_small/57554544.jpg",
            "image_url_cropped": "https://images.ygoprodeck.com/images/cards_cropped/57554544.jpg"
          }
        ]
      },
      {
        "id": 39733924,
        "name": "Full-Armored Xyz",
        "card_images": [
          {
            "id": 39733924,
            "image_url": "https://images.ygoprodeck.com/images/cards/39733924.jpg",
            "image_url_small": "https://images.ygoprodeck.com/images/cards_small/39733924.jpg",
            "image_url_cropped": "https://images.ygoprodeck.com/images/cards_cropped/39733924.jpg"
          }
        ]
      },
      {
        "id": 59432181,
        "name": "Fusion Tag",
        "card_images": [
          {
            "id": 59432181,
            "image_url": "https://images.ygoprodeck.com/images/cards/59432181.jpg",
            "image_url_small": "https://images.ygoprodeck.com/images/cards_small/59432181.jpg",
            "image_url_cropped": "https://images.ygoprodeck.com/images/cards_cropped/59432181.jpg"
          }
        ]
      },
      {
        "id": 34822851,
        "name": "Infernoid Token",
        "card_images": [
          {
            "id": 34822851,
            "image_url": "https://images.ygoprodeck.com/images/cards/34822851.jpg",
            "image_url_small": "https://images.ygoprodeck.com/images/cards_small/34822851.jpg",
            "image_url_cropped": "https://images.ygoprodeck.com/images/cards_cropped/34822851.jpg"
          }
        ]
      },
      {
        "id": 74203495,
        "name": "PSY-Framegear Delta",
        "card_images": [
          {
            "id": 74203495,
            "image_url": "https://images.ygoprodeck.com/images/cards/74203495.jpg",
            "image_url_small": "https://images.ygoprodeck.com/images/cards_small/74203495.jpg",
            "image_url_cropped": "https://images.ygoprodeck.com/images/cards_cropped/74203495.jpg"
          }
        ]
      },
      {
        "id": 5758500,
        "name": "Soul Release",
        "card_images": [
          {
            "id": 5758500,
            "image_url": "https://images.ygoprodeck.com/images/cards/5758500.jpg",
            "image_url_small": "https://images.ygoprodeck.com/images/cards_small/5758500.jpg",
            "image_url_cropped": "https://images.ygoprodeck.com/images/cards_cropped/5758500.jpg"
          }
        ]
      },
      {
        "id": 57473560,
        "name": "Wightprince",
        "card_images": [
          {
            "id": 57473560,
            "image_url": "https://images.ygoprodeck.com/images/cards/57473560.jpg",
            "image_url_small": "https://images.ygoprodeck.com/images/cards_small/57473560.jpg",
            "image_url_cropped": "https://images.ygoprodeck.com/images/cards_cropped/57473560.jpg"
          }
        ]
      },
      {
        "id": 90243945,
        "name": "Wightprincess",
        "card_images": [
          {
            "id": 90243945,
            "image_url": "https://images.ygoprodeck.com/images/cards/90243945.jpg",
            "image_url_small": "https://images.ygoprodeck.com/images/cards_small/90243945.jpg",
            "image_url_cropped": "https://images.ygoprodeck.com/images/cards_cropped/90243945.jpg"
          }
        ]
      }
    ],
    "rare": [],
    "common": [
      {
        "id": 9464441,
        "name": "Adamancipator Risen - Dragite",
        "card_images": [
          {
            "id": 9464441,
            "image_url": "https://images.ygoprodeck.com/images/cards/9464441.jpg",
            "image_url_small": "https://images.ygoprodeck.com/images/cards_small/9464441.jpg",
            "image_url_cropped": "https://images.ygoprodeck.com/images/cards_cropped/9464441.jpg"
          }
        ]
      },
      {
        "id": 15177750,
        "name": "Blessed Winds",
        "card_images": [
          {
            "id": 15177750,
            "image_url": "https://images.ygoprodeck.com/images/cards/15177750.jpg",
            "image_url_small": "https://images.ygoprodeck.com/images/cards_small/15177750.jpg",
            "image_url_cropped": "https://images.ygoprodeck.com/images/cards_cropped/15177750.jpg"
          }
        ]
      },
      {
        "id": 28265983,
        "name": "Dried Winds",
        "card_images": [
          {
            "id": 28265983,
            "image_url": "https://images.ygoprodeck.com/images/cards/28265983.jpg",
            "image_url_small": "https://images.ygoprodeck.com/images/cards_small/28265983.jpg",
            "image_url_cropped": "https://images.ygoprodeck.com/images/cards_cropped/28265983.jpg"
          }
        ]
      },
      {
        "id": 89333528,
        "name": "Genex Gaia",
        "card_images": [
          {
            "id": 89333528,
            "image_url": "https://images.ygoprodeck.com/images/cards/89333528.jpg",
            "image_url_small": "https://images.ygoprodeck.com/images/cards_small/89333528.jpg",
            "image_url_cropped": "https://images.ygoprodeck.com/images/cards_cropped/89333528.jpg"
          }
        ]
      },
      {
        "id": 4904812,
        "name": "Genex Undine",
        "card_images": [
          {
            "id": 4904812,
            "image_url": "https://images.ygoprodeck.com/images/cards/4904812.jpg",
            "image_url_small": "https://images.ygoprodeck.com/images/cards_small/4904812.jpg",
            "image_url_cropped": "https://images.ygoprodeck.com/images/cards_cropped/4904812.jpg"
          }
        ]
      },
      {
        "id": 92266279,
        "name": "Humid Winds",
        "card_images": [
          {
            "id": 92266279,
            "image_url": "https://images.ygoprodeck.com/images/cards/92266279.jpg",
            "image_url_small": "https://images.ygoprodeck.com/images/cards_small/92266279.jpg",
            "image_url_cropped": "https://images.ygoprodeck.com/images/cards_cropped/92266279.jpg"
          }
        ]
      },
      {
        "id": 65676461,
        "name": "Number 32: Shark Drake",
        "card_images": [
          {
            "id": 65676461,
            "image_url": "https://images.ygoprodeck.com/images/cards/65676461.jpg",
            "image_url_small": "https://images.ygoprodeck.com/images/cards_small/65676461.jpg",
            "image_url_cropped": "https://images.ygoprodeck.com/images/cards_cropped/65676461.jpg"
          }
        ]
      },
      {
        "id": 36429703,
        "name": "Raidraptor - Wise Strix",
        "card_images": [
          {
            "id": 36429703,
            "image_url": "https://images.ygoprodeck.com/images/cards/36429703.jpg",
            "image_url_small": "https://images.ygoprodeck.com/images/cards_small/36429703.jpg",
            "image_url_cropped": "https://images.ygoprodeck.com/images/cards_cropped/36429703.jpg"
          }
        ]
      },
      {
        "id": 58988903,
        "name": "Rank-Up-Magic Skip Force",
        "card_images": [
          {
            "id": 58988903,
            "image_url": "https://images.ygoprodeck.com/images/cards/58988903.jpg",
            "image_url_small": "https://images.ygoprodeck.com/images/cards_small/58988903.jpg",
            "image_url_cropped": "https://images.ygoprodeck.com/images/cards_cropped/58988903.jpg"
          }
        ]
      },
      {
        "id": 90411554,
        "name": "Redox, Dragon Ruler of Boulders",
        "card_images": [
          {
            "id": 90411554,
            "image_url": "https://images.ygoprodeck.com/images/cards/90411554.jpg",
            "image_url_small": "https://images.ygoprodeck.com/images/cards_small/90411554.jpg",
            "image_url_cropped": "https://images.ygoprodeck.com/images/cards_cropped/90411554.jpg"
          }
        ]
      },
      {
        "id": 71829750,
        "name": "Serpentine Princess",
        "card_images": [
          {
            "id": 71829750,
            "image_url": "https://images.ygoprodeck.com/images/cards/71829750.jpg",
            "image_url_small": "https://images.ygoprodeck.com/images/cards_small/71829750.jpg",
            "image_url_cropped": "https://images.ygoprodeck.com/images/cards_cropped/71829750.jpg"
          }
        ]
      },
      {
        "id": 26866984,
        "name": "Trias Hierarchia",
        "card_images": [
          {
            "id": 26866984,
            "image_url": "https://images.ygoprodeck.com/images/cards/26866984.jpg",
            "image_url_small": "https://images.ygoprodeck.com/images/cards_small/26866984.jpg",
            "image_url_cropped": "https://images.ygoprodeck.com/images/cards_cropped/26866984.jpg"
          }
        ]
      },
      {
        "id": 8512558,
        "name": "Utopic Onomatopoeia",
        "card_images": [
          {
            "id": 8512558,
            "image_url": "https://images.ygoprodeck.com/images/cards/8512558.jpg",
            "image_url_small": "https://images.ygoprodeck.com/images/cards_small/8512558.jpg",
            "image_url_cropped": "https://images.ygoprodeck.com/images/cards_cropped/8512558.jpg"
          }
        ]
      },
      {
        "id": 92519087,
        "name": "Virtual World Kyubi - Shenshen",
        "card_images": [
          {
            "id": 92519087,
            "image_url": "https://images.ygoprodeck.com/images/cards/92519087.jpg",
            "image_url_small": "https://images.ygoprodeck.com/images/cards_small/92519087.jpg",
            "image_url_cropped": "https://images.ygoprodeck.com/images/cards_cropped/92519087.jpg"
          }
        ]
      }
    ]
  }
}