{
  "setName": "Star Pack Battle Royal",
  "rarities": {
    "secret": [],
    "ultra": [],
    "super": [],
    "rare": [],
    "common": [
      {
        "id": 84988419,
        "name": "Bloom Diva the Melodious Choir",
        "card_images": [
          {
            "id": 84988419,
            "image_url": "https://images.ygoprodeck.com/images/cards/84988419.jpg",
            "image_url_small": "https://images.ygoprodeck.com/images/cards_small/84988419.jpg",
            "image_url_cropped": "https://images.ygoprodeck.com/images/cards_cropped/84988419.jpg"
          },
          {
            "id": 84988419,
            "image_url": "https://images.ygoprodeck.com/images/cards/84988419.jpg",
            "image_url_small": "https://images.ygoprodeck.com/images/cards_small/84988419.jpg",
            "image_url_cropped": "https://images.ygoprodeck.com/images/cards_cropped/84988419.jpg"
          }
        ]
      },
      {
        "id": 24672164,
        "name": "Bloom Prima the Melodious Choir",
        "card_images": [
          {
            "id": 24672164,
            "image_url": "https://images.ygoprodeck.com/images/cards/24672164.jpg",
            "image_url_small": "https://images.ygoprodeck.com/images/cards_small/24672164.jpg",
            "image_url_cropped": "https://images.ygoprodeck.com/images/cards_cropped/24672164.jpg"
          },
          {
            "id": 24672164,
            "image_url": "https://images.ygoprodeck.com/images/cards/24672164.jpg",
            "image_url_small": "https://images.ygoprodeck.com/images/cards_small/24672164.jpg",
            "image_url_cropped": "https://images.ygoprodeck.com/images/cards_cropped/24672164.jpg"
          }
        ]
      },
      {
        "id": 79531196,
        "name": "Crystal Rose",
        "card_images": [
          {
            "id": 79531196,
            "image_url": "https://images.ygoprodeck.com/images/cards/79531196.jpg",
            "image_url_small": "https://images.ygoprodeck.com/images/cards_small/79531196.jpg",
            "image_url_cropped": "https://images.ygoprodeck.com/images/cards_cropped/79531196.jpg"
          },
          {
            "id": 79531196,
            "image_url": "https://images.ygoprodeck.com/images/cards/79531196.jpg",
            "image_url_small": "https://images.ygoprodeck.com/images/cards_small/79531196.jpg",
            "image_url_cropped": "https://images.ygoprodeck.com/images/cards_cropped/79531196.jpg"
          }
        ]
      },
      {
        "id": 72291412,
        "name": "D/D Necro Slime",
        "card_images": [
          {
            "id": 72291412,
            "image_url": "https://images.ygoprodeck.com/images/cards/72291412.jpg",
            "image_url_small": "https://images.ygoprodeck.com/images/cards_small/72291412.jpg",
            "image_url_cropped": "https://images.ygoprodeck.com/images/cards_cropped/72291412.jpg"
          },
          {
            "id": 72291412,
            "image_url": "https://images.ygoprodeck.com/images/cards/72291412.jpg",
            "image_url_small": "https://images.ygoprodeck.com/images/cards_small/72291412.jpg",
            "image_url_cropped": "https://images.ygoprodeck.com/images/cards_cropped/72291412.jpg"
          }
        ]
      },
      {
        "id": 45206713,
        "name": "D/D Swirl Slime",
        "card_images": [
          {
            "id": 45206713,
            "image_url": "https://images.ygoprodeck.com/images/cards/45206713.jpg",
            "image_url_small": "https://images.ygoprodeck.com/images/cards_small/45206713.jpg",
            "image_url_cropped": "https://images.ygoprodeck.com/images/cards_cropped/45206713.jpg"
          },
          {
            "id": 45206713,
            "image_url": "https://images.ygoprodeck.com/images/cards/45206713.jpg",
            "image_url_small": "https://images.ygoprodeck.com/images/cards_small/45206713.jpg",
            "image_url_cropped": "https://images.ygoprodeck.com/images/cards_cropped/45206713.jpg"
          }
        ]
      },
      {
        "id": 15939229,
        "name": "D/D/D Duo-Dawn King Kali Yuga",
        "card_images": [
          {
            "id": 15939229,
            "image_url": "https://images.ygoprodeck.com/images/cards/15939229.jpg",
            "image_url_small": "https://images.ygoprodeck.com/images/cards_small/15939229.jpg",
            "image_url_cropped": "https://images.ygoprodeck.com/images/cards_cropped/15939229.jpg"
          },
          {
            "id": 15939229,
            "image_url": "https://images.ygoprodeck.com/images/cards/15939229.jpg",
            "image_url_small": "https://images.ygoprodeck.com/images/cards_small/15939229.jpg",
            "image_url_cropped": "https://images.ygoprodeck.com/images/cards_cropped/15939229.jpg"
          }
        ]
      },
      {
        "id": 74069667,
        "name": "D/D/D Oblivion King Abyss Ragnarok",
        "card_images": [
          {
            "id": 74069667,
            "image_url": "https://images.ygoprodeck.com/images/cards/74069667.jpg",
            "image_url_small": "https://images.ygoprodeck.com/images/cards_small/74069667.jpg",
            "image_url_cropped": "https://images.ygoprodeck.com/images/cards_cropped/74069667.jpg"
          },
          {
            "id": 74069667,
            "image_url": "https://images.ygoprodeck.com/images/cards/74069667.jpg",
            "image_url_small": "https://images.ygoprodeck.com/images/cards_small/74069667.jpg",
            "image_url_cropped": "https://images.ygoprodeck.com/images/cards_cropped/74069667.jpg"
          }
        ]
      },
      {
        "id": 82956492,
        "name": "D/D/D Oracle King d'Arc",
        "card_images": [
          {
            "id": 82956492,
            "image_url": "https://images.ygoprodeck.com/images/cards/82956492.jpg",
            "image_url_small": "https://images.ygoprodeck.com/images/cards_small/82956492.jpg",
            "image_url_cropped": "https://images.ygoprodeck.com/images/cards_cropped/82956492.jpg"
          },
          {
            "id": 82956492,
            "image_url": "https://images.ygoprodeck.com/images/cards/82956492.jpg",
            "image_url_small": "https://images.ygoprodeck.com/images/cards_small/82956492.jpg",
            "image_url_cropped": "https://images.ygoprodeck.com/images/cards_cropped/82956492.jpg"
          }
        ]
      },
      {
        "id": 34688023,
        "name": "Edge Imp Saw",
        "card_images": [
          {
            "id": 34688023,
            "image_url": "https://images.ygoprodeck.com/images/cards/34688023.jpg",
            "image_url_small": "https://images.ygoprodeck.com/images/cards_small/34688023.jpg",
            "image_url_cropped": "https://images.ygoprodeck.com/images/cards_cropped/34688023.jpg"
          },
          {
            "id": 34688023,
            "image_url": "https://images.ygoprodeck.com/images/cards/34688023.jpg",
            "image_url_small": "https://images.ygoprodeck.com/images/cards_small/34688023.jpg",
            "image_url_cropped": "https://images.ygoprodeck.com/images/cards_cropped/34688023.jpg"
          }
        ]
      },
      {
        "id": 66457138,
        "name": "Fluffal Leo",
        "card_images": [
          {
            "id": 66457138,
            "image_url": "https://images.ygoprodeck.com/images/cards/66457138.jpg",
            "image_url_small": "https://images.ygoprodeck.com/images/cards_small/66457138.jpg",
            "image_url_cropped": "https://images.ygoprodeck.com/images/cards_cropped/66457138.jpg"
          },
          {
            "id": 66457138,
            "image_url": "https://images.ygoprodeck.com/images/cards/66457138.jpg",
            "image_url_small": "https://images.ygoprodeck.com/images/cards_small/66457138.jpg",
            "image_url_cropped": "https://images.ygoprodeck.com/images/cards_cropped/66457138.jpg"
          }
        ]
      },
      {
        "id": 98280324,
        "name": "Fluffal Sheep",
        "card_images": [
          {
            "id": 98280324,
            "image_url": "https://images.ygoprodeck.com/images/cards/98280324.jpg",
            "image_url_small": "https://images.ygoprodeck.com/images/cards_small/98280324.jpg",
            "image_url_cropped": "https://images.ygoprodeck.com/images/cards_cropped/98280324.jpg"
          },
          {
            "id": 98280324,
            "image_url": "https://images.ygoprodeck.com/images/cards/98280324.jpg",
            "image_url_small": "https://images.ygoprodeck.com/images/cards_small/98280324.jpg",
            "image_url_cropped": "https://images.ygoprodeck.com/images/cards_cropped/98280324.jpg"
          }
        ]
      },
      {
        "id": 83866861,
        "name": "Frightfur Chimera",
        "card_images": [
          {
            "id": 83866861,
            "image_url": "https://images.ygoprodeck.com/images/cards/83866861.jpg",
            "image_url_small": "https://images.ygoprodeck.com/images/cards_small/83866861.jpg",
            "image_url_cropped": "https://images.ygoprodeck.com/images/cards_cropped/83866861.jpg"
          },
          {
            "id": 83866861,
            "image_url": "https://images.ygoprodeck.com/images/cards/83866861.jpg",
            "image_url_small": "https://images.ygoprodeck.com/images/cards_small/83866861.jpg",
            "image_url_cropped": "https://images.ygoprodeck.com/images/cards_cropped/83866861.jpg"
          }
        ]
      },
      {
        "id": 6077601,
        "name": "Frightfur Fusion",
        "card_images": [
          {
            "id": 6077601,
            "image_url": "https://images.ygoprodeck.com/images/cards/6077601.jpg",
            "image_url_small": "https://images.ygoprodeck.com/images/cards_small/6077601.jpg",
            "image_url_cropped": "https://images.ygoprodeck.com/images/cards_cropped/6077601.jpg"
          },
          {
            "id": 6077601,
            "image_url": "https://images.ygoprodeck.com/images/cards/6077601.jpg",
            "image_url_small": "https://images.ygoprodeck.com/images/cards_small/6077601.jpg",
            "image_url_cropped": "https://images.ygoprodeck.com/images/cards_cropped/6077601.jpg"
          }
        ]
      },
      {
        "id": 10383554,
        "name": "Frightfur Leo",
        "card_images": [
          {
            "id": 10383554,
            "image_url": "https://images.ygoprodeck.com/images/cards/10383554.jpg",
            "image_url_small": "https://images.ygoprodeck.com/images/cards_small/10383554.jpg",
            "image_url_cropped": "https://images.ygoprodeck.com/images/cards_cropped/10383554.jpg"
          },
          {
            "id": 10383554,
            "image_url": "https://images.ygoprodeck.com/images/cards/10383554.jpg",
            "image_url_small": "https://images.ygoprodeck.com/images/cards_small/10383554.jpg",
            "image_url_cropped": "https://images.ygoprodeck.com/images/cards_cropped/10383554.jpg"
          }
        ]
      },
      {
        "id": 57477163,
        "name": "Frightfur Sheep",
        "card_images": [
          {
            "id": 57477163,
            "image_url": "https://images.ygoprodeck.com/images/cards/57477163.jpg",
            "image_url_small": "https://images.ygoprodeck.com/images/cards_small/57477163.jpg",
            "image_url_cropped": "https://images.ygoprodeck.com/images/cards_cropped/57477163.jpg"
          },
          {
            "id": 57477163,
            "image_url": "https://images.ygoprodeck.com/images/cards/57477163.jpg",
            "image_url_small": "https://images.ygoprodeck.com/images/cards_small/57477163.jpg",
            "image_url_cropped": "https://images.ygoprodeck.com/images/cards_cropped/57477163.jpg"
          }
        ]
      },
      {
        "id": 97007933,
        "name": "Hi-Speedroid Kendama",
        "card_images": [
          {
            "id": 97007933,
            "image_url": "https://images.ygoprodeck.com/images/cards/97007933.jpg",
            "image_url_small": "https://images.ygoprodeck.com/images/cards_small/97007933.jpg",
            "image_url_cropped": "https://images.ygoprodeck.com/images/cards_cropped/97007933.jpg"
          },
          {
            "id": 97007933,
            "image_url": "https://images.ygoprodeck.com/images/cards/97007933.jpg",
            "image_url_small": "https://images.ygoprodeck.com/images/cards_small/97007933.jpg",
            "image_url_cropped": "https://images.ygoprodeck.com/images/cards_cropped/97007933.jpg"
          }
        ]
      },
      {
        "id": 93368494,
        "name": "Mayosenju Daibak",
        "card_images": [
          {
            "id": 93368494,
            "image_url": "https://images.ygoprodeck.com/images/cards/93368494.jpg",
            "image_url_small": "https://images.ygoprodeck.com/images/cards_small/93368494.jpg",
            "image_url_cropped": "https://images.ygoprodeck.com/images/cards_cropped/93368494.jpg"
          },
          {
            "id": 93368494,
            "image_url": "https://images.ygoprodeck.com/images/cards/93368494.jpg",
            "image_url_small": "https://images.ygoprodeck.com/images/cards_small/93368494.jpg",
            "image_url_cropped": "https://images.ygoprodeck.com/images/cards_cropped/93368494.jpg"
          }
        ]
      },
      {
        "id": 43268675,
        "name": "Opera the Melodious Diva",
        "card_images": [
          {
            "id": 43268675,
            "image_url": "https://images.ygoprodeck.com/images/cards/43268675.jpg",
            "image_url_small": "https://images.ygoprodeck.com/images/cards_small/43268675.jpg",
            "image_url_cropped": "https://images.ygoprodeck.com/images/cards_cropped/43268675.jpg"
          },
          {
            "id": 43268675,
            "image_url": "https://images.ygoprodeck.com/images/cards/43268675.jpg",
            "image_url_small": "https://images.ygoprodeck.com/images/cards_small/43268675.jpg",
            "image_url_cropped": "https://images.ygoprodeck.com/images/cards_cropped/43268675.jpg"
          }
        ]
      },
      {
        "id": 70479321,
        "name": "Performapal Drummerilla",
        "card_images": [
          {
            "id": 70479321,
            "image_url": "https://images.ygoprodeck.com/images/cards/70479321.jpg",
            "image_url_small": "https://images.ygoprodeck.com/images/cards_small/70479321.jpg",
            "image_url_cropped": "https://images.ygoprodeck.com/images/cards_cropped/70479321.jpg"
          },
          {
            "id": 70479321,
            "image_url": "https://images.ygoprodeck.com/images/cards/70479321.jpg",
            "image_url_small": "https://images.ygoprodeck.com/images/cards_small/70479321.jpg",
            "image_url_cropped": "https://images.ygoprodeck.com/images/cards_cropped/70479321.jpg"
          }
        ]
      },
      {
        "id": 12255007,
        "name": "Performapal Fireflux",
        "card_images": [
          {
            "id": 12255007,
            "image_url": "https://images.ygoprodeck.com/images/cards/12255007.jpg",
            "image_url_small": "https://images.ygoprodeck.com/images/cards_small/12255007.jpg",
            "image_url_cropped": "https://images.ygoprodeck.com/images/cards_cropped/12255007.jpg"
          },
          {
            "id": 12255007,
            "image_url": "https://images.ygoprodeck.com/images/cards/12255007.jpg",
            "image_url_small": "https://images.ygoprodeck.com/images/cards_small/12255007.jpg",
            "image_url_cropped": "https://images.ygoprodeck.com/images/cards_cropped/12255007.jpg"
          }
        ]
      },
      {
        "id": 59762399,
        "name": "Performapal Odd-Eyes Light Phoenix",
        "card_images": [
          {
            "id": 59762399,
            "image_url": "https://images.ygoprodeck.com/images/cards/59762399.jpg",
            "image_url_small": "https://images.ygoprodeck.com/images/cards_small/59762399.jpg",
            "image_url_cropped": "https://images.ygoprodeck.com/images/cards_cropped/59762399.jpg"
          },
          {
            "id": 59762399,
            "image_url": "https://images.ygoprodeck.com/images/cards/59762399.jpg",
            "image_url_small": "https://images.ygoprodeck.com/images/cards_small/59762399.jpg",
            "image_url_cropped": "https://images.ygoprodeck.com/images/cards_cropped/59762399.jpg"
          }
        ]
      },
      {
        "id": 86157908,
        "name": "Performapal Odd-Eyes Unicorn",
        "card_images": [
          {
            "id": 86157908,
            "image_url": "https://images.ygoprodeck.com/images/cards/86157908.jpg",
            "image_url_small": "https://images.ygoprodeck.com/images/cards_small/86157908.jpg",
            "image_url_cropped": "https://images.ygoprodeck.com/images/cards_cropped/86157908.jpg"
          },
          {
            "id": 86157908,
            "image_url": "https://images.ygoprodeck.com/images/cards/86157908.jpg",
            "image_url_small": "https://images.ygoprodeck.com/images/cards_small/86157908.jpg",
            "image_url_cropped": "https://images.ygoprodeck.com/images/cards_cropped/86157908.jpg"
          }
        ]
      },
      {
        "id": 15978426,
        "name": "Performapal Secondonkey",
        "card_images": [
          {
            "id": 15978426,
            "image_url": "https://images.ygoprodeck.com/images/cards/15978426.jpg",
            "image_url_small": "https://images.ygoprodeck.com/images/cards_small/15978426.jpg",
            "image_url_cropped": "https://images.ygoprodeck.com/images/cards_cropped/15978426.jpg"
          },
          {
            "id": 15978426,
            "image_url": "https://images.ygoprodeck.com/images/cards/15978426.jpg",
            "image_url_small": "https://images.ygoprodeck.com/images/cards_small/15978426.jpg",
            "image_url_cropped": "https://images.ygoprodeck.com/images/cards_cropped/15978426.jpg"
          }
        ]
      },
      {
        "id": 70458081,
        "name": "Performapal Thunderhino",
        "card_images": [
          {
            "id": 70458081,
            "image_url": "https://images.ygoprodeck.com/images/cards/70458081.jpg",
            "image_url_small": "https://images.ygoprodeck.com/images/cards_small/70458081.jpg",
            "image_url_cropped": "https://images.ygoprodeck.com/images/cards_cropped/70458081.jpg"
          },
          {
            "id": 70458081,
            "image_url": "https://images.ygoprodeck.com/images/cards/70458081.jpg",
            "image_url_small": "https://images.ygoprodeck.com/images/cards_small/70458081.jpg",
            "image_url_cropped": "https://images.ygoprodeck.com/images/cards_cropped/70458081.jpg"
          }
        ]
      },
      {
        "id": 70899775,
        "name": "Pianissimo",
        "card_images": [
          {
            "id": 70899775,
            "image_url": "https://images.ygoprodeck.com/images/cards/70899775.jpg",
            "image_url_small": "https://images.ygoprodeck.com/images/cards_small/70899775.jpg",
            "image_url_cropped": "https://images.ygoprodeck.com/images/cards_cropped/70899775.jpg"
          },
          {
            "id": 70899775,
            "image_url": "https://images.ygoprodeck.com/images/cards/70899775.jpg",
            "image_url_small": "https://images.ygoprodeck.com/images/cards_small/70899775.jpg",
            "image_url_cropped": "https://images.ygoprodeck.com/images/cards_cropped/70899775.jpg"
          }
        ]
      },
      {
        "id": 57594700,
        "name": "Schuberta the Melodious Maestra",
        "card_images": [
          {
            "id": 57594700,
            "image_url": "https://images.ygoprodeck.com/images/cards/57594700.jpg",
            "image_url_small": "https://images.ygoprodeck.com/images/cards_small/57594700.jpg",
            "image_url_cropped": "https://images.ygoprodeck.com/images/cards_cropped/57594700.jpg"
          },
          {
            "id": 57594700,
            "image_url": "https://images.ygoprodeck.com/images/cards/57594700.jpg",
            "image_url_small": "https://images.ygoprodeck.com/images/cards_small/57594700.jpg",
            "image_url_cropped": "https://images.ygoprodeck.com/images/cards_cropped/57594700.jpg"
          }
        ]
      },
      {
        "id": 41767843,
        "name": "Score the Melodious Diva",
        "card_images": [
          {
            "id": 41767843,
            "image_url": "https://images.ygoprodeck.com/images/cards/41767843.jpg",
            "image_url_small": "https://images.ygoprodeck.com/images/cards_small/41767843.jpg",
            "image_url_cropped": "https://images.ygoprodeck.com/images/cards_cropped/41767843.jpg"
          },
          {
            "id": 41767843,
            "image_url": "https://images.ygoprodeck.com/images/cards/41767843.jpg",
            "image_url_small": "https://images.ygoprodeck.com/images/cards_small/41767843.jpg",
            "image_url_cropped": "https://images.ygoprodeck.com/images/cards_cropped/41767843.jpg"
          }
        ]
      },
      {
        "id": 14763299,
        "name": "Solo the Melodious Songstress",
        "card_images": [
          {
            "id": 14763299,
            "image_url": "https://images.ygoprodeck.com/images/cards/14763299.jpg",
            "image_url_small": "https://images.ygoprodeck.com/images/cards_small/14763299.jpg",
            "image_url_cropped": "https://images.ygoprodeck.com/images/cards_cropped/14763299.jpg"
          },
          {
            "id": 14763299,
            "image_url": "https://images.ygoprodeck.com/images/cards/14763299.jpg",
            "image_url_small": "https://images.ygoprodeck.com/images/cards_small/14763299.jpg",
            "image_url_cropped": "https://images.ygoprodeck.com/images/cards_cropped/14763299.jpg"
          }
        ]
      },
      {
        "id": 62895219,
        "name": "Soprano the Melodious Songstress",
        "card_images": [
          {
            "id": 62895219,
            "image_url": "https://images.ygoprodeck.com/images/cards/62895219.jpg",
            "image_url_small": "https://images.ygoprodeck.com/images/cards_small/62895219.jpg",
            "image_url_cropped": "https://images.ygoprodeck.com/images/cards_cropped/62895219.jpg"
          },
          {
            "id": 62895219,
            "image_url": "https://images.ygoprodeck.com/images/cards/62895219.jpg",
            "image_url_small": "https://images.ygoprodeck.com/images/cards_small/62895219.jpg",
            "image_url_cropped": "https://images.ygoprodeck.com/images/cards_cropped/62895219.jpg"
          }
        ]
      },
      {
        "id": 88204302,
        "name": "Speed Recovery",
        "card_images": [
          {
            "id": 88204302,
            "image_url": "https://images.ygoprodeck.com/images/cards/88204302.jpg",
            "image_url_small": "https://images.ygoprodeck.com/images/cards_small/88204302.jpg",
            "image_url_cropped": "https://images.ygoprodeck.com/images/cards_cropped/88204302.jpg"
          },
          {
            "id": 88204302,
            "image_url": "https://images.ygoprodeck.com/images/cards/88204302.jpg",
            "image_url_small": "https://images.ygoprodeck.com/images/cards_small/88204302.jpg",
            "image_url_cropped": "https://images.ygoprodeck.com/images/cards_cropped/88204302.jpg"
          }
        ]
      },
      {
        "id": 53054833,
        "name": "Speedroid Double Yoyo",
        "card_images": [
          {
            "id": 53054833,
            "image_url": "https://images.ygoprodeck.com/images/cards/53054833.jpg",
            "image_url_small": "https://images.ygoprodeck.com/images/cards_small/53054833.jpg",
            "image_url_cropped": "https://images.ygoprodeck.com/images/cards_cropped/53054833.jpg"
          },
          {
            "id": 53054833,
            "image_url": "https://images.ygoprodeck.com/images/cards/53054833.jpg",
            "image_url_small": "https://images.ygoprodeck.com/images/cards_small/53054833.jpg",
            "image_url_cropped": "https://images.ygoprodeck.com/images/cards_cropped/53054833.jpg"
          }
        ]
      },
      {
        "id": 81275020,
        "name": "Speedroid Terrortop",
        "card_images": [
          {
            "id": 81275020,
            "image_url": "https://images.ygoprodeck.com/images/cards/81275020.jpg",
            "image_url_small": "https://images.ygoprodeck.com/images/cards_small/81275020.jpg",
            "image_url_cropped": "https://images.ygoprodeck.com/images/cards_cropped/81275020.jpg"
          },
          {
            "id": 81275020,
            "image_url": "https://images.ygoprodeck.com/images/cards/81275020.jpg",
            "image_url_small": "https://images.ygoprodeck.com/images/cards_small/81275020.jpg",
            "image_url_cropped": "https://images.ygoprodeck.com/images/cards_cropped/81275020.jpg"
          }
        ]
      },
      {
        "id": 27660735,
        "name": "Speedroid Tri-Eyed Dice",
        "card_images": [
          {
            "id": 27660735,
            "image_url": "https://images.ygoprodeck.com/images/cards/27660735.jpg",
            "image_url_small": "https://images.ygoprodeck.com/images/cards_small/27660735.jpg",
            "image_url_cropped": "https://images.ygoprodeck.com/images/cards_cropped/27660735.jpg"
          },
          {
            "id": 27660735,
            "image_url": "https://images.ygoprodeck.com/images/cards/27660735.jpg",
            "image_url_small": "https://images.ygoprodeck.com/images/cards_small/27660735.jpg",
            "image_url_cropped": "https://images.ygoprodeck.com/images/cards_cropped/27660735.jpg"
          }
        ]
      },
      {
        "id": 9402966,
        "name": "Superheavy Samurai Battleball",
        "card_images": [
          {
            "id": 9402966,
            "image_url": "https://images.ygoprodeck.com/images/cards/9402966.jpg",
            "image_url_small": "https://images.ygoprodeck.com/images/cards_small/9402966.jpg",
            "image_url_cropped": "https://images.ygoprodeck.com/images/cards_cropped/9402966.jpg"
          },
          {
            "id": 9402966,
            "image_url": "https://images.ygoprodeck.com/images/cards/9402966.jpg",
            "image_url_small": "https://images.ygoprodeck.com/images/cards_small/9402966.jpg",
            "image_url_cropped": "https://images.ygoprodeck.com/images/cards_cropped/9402966.jpg"
          }
        ]
      },
      {
        "id": 36523152,
        "name": "Superheavy Samurai Big Waraji",
        "card_images": [
          {
            "id": 36523152,
            "image_url": "https://images.ygoprodeck.com/images/cards/36523152.jpg",
            "image_url_small": "https://images.ygoprodeck.com/images/cards_small/36523152.jpg",
            "image_url_cropped": "https://images.ygoprodeck.com/images/cards_cropped/36523152.jpg"
          },
          {
            "id": 36523152,
            "image_url": "https://images.ygoprodeck.com/images/cards/36523152.jpg",
            "image_url_small": "https://images.ygoprodeck.com/images/cards_small/36523152.jpg",
            "image_url_cropped": "https://images.ygoprodeck.com/images/cards_cropped/36523152.jpg"
          }
        ]
      },
      {
        "id": 62017867,
        "name": "Superheavy Samurai Gigagloves",
        "card_images": [
          {
            "id": 62017867,
            "image_url": "https://images.ygoprodeck.com/images/cards/62017867.jpg",
            "image_url_small": "https://images.ygoprodeck.com/images/cards_small/62017867.jpg",
            "image_url_cropped": "https://images.ygoprodeck.com/images/cards_cropped/62017867.jpg"
          },
          {
            "id": 62017867,
            "image_url": "https://images.ygoprodeck.com/images/cards/62017867.jpg",
            "image_url_small": "https://images.ygoprodeck.com/images/cards_small/62017867.jpg",
            "image_url_cropped": "https://images.ygoprodeck.com/images/cards_cropped/62017867.jpg"
          }
        ]
      },
      {
        "id": 36953371,
        "name": "Superheavy Samurai Ogre Shutendoji",
        "card_images": [
          {
            "id": 36953371,
            "image_url": "https://images.ygoprodeck.com/images/cards/36953371.jpg",
            "image_url_small": "https://images.ygoprodeck.com/images/cards_small/36953371.jpg",
            "image_url_cropped": "https://images.ygoprodeck.com/images/cards_cropped/36953371.jpg"
          },
          {
            "id": 36953371,
            "image_url": "https://images.ygoprodeck.com/images/cards/36953371.jpg",
            "image_url_small": "https://images.ygoprodeck.com/images/cards_small/36953371.jpg",
            "image_url_cropped": "https://images.ygoprodeck.com/images/cards_cropped/36953371.jpg"
          }
        ]
      },
      {
        "id": 35800511,
        "name": "Superheavy Samurai Soulbuster Gauntlet",
        "card_images": [
          {
            "id": 35800511,
            "image_url": "https://images.ygoprodeck.com/images/cards/35800511.jpg",
            "image_url_small": "https://images.ygoprodeck.com/images/cards_small/35800511.jpg",
            "image_url_cropped": "https://images.ygoprodeck.com/images/cards_cropped/35800511.jpg"
          },
          {
            "id": 35800511,
            "image_url": "https://images.ygoprodeck.com/images/cards/35800511.jpg",
            "image_url_small": "https://images.ygoprodeck.com/images/cards_small/35800511.jpg",
            "image_url_cropped": "https://images.ygoprodeck.com/images/cards_cropped/35800511.jpg"
          }
        ]
      },
      {
        "id": 3643300,
        "name": "The Legendary Fisherman",
        "card_images": [
          {
            "id": 3643300,
            "image_url": "https://images.ygoprodeck.com/images/cards/3643300.jpg",
            "image_url_small": "https://images.ygoprodeck.com/images/cards_small/3643300.jpg",
            "image_url_cropped": "https://images.ygoprodeck.com/images/cards_cropped/3643300.jpg"
          },
          {
            "id": 3643300,
            "image_url": "https://images.ygoprodeck.com/images/cards/3643300.jpg",
            "image_url_small": "https://images.ygoprodeck.com/images/cards_small/3643300.jpg",
            "image_url_cropped": "https://images.ygoprodeck.com/images/cards_cropped/3643300.jpg"
          }
        ]
      },
      {
        "id": 44968687,
        "name": "The Legendary Fisherman III",
        "card_images": [
          {
            "id": 44968687,
            "image_url": "https://images.ygoprodeck.com/images/cards/44968687.jpg",
            "image_url_small": "https://images.ygoprodeck.com/images/cards_small/44968687.jpg",
            "image_url_cropped": "https://images.ygoprodeck.com/images/cards_cropped/44968687.jpg"
          },
          {
            "id": 44968687,
            "image_url": "https://images.ygoprodeck.com/images/cards/44968687.jpg",
            "image_url_small": "https://images.ygoprodeck.com/images/cards_small/44968687.jpg",
            "image_url_cropped": "https://images.ygoprodeck.com/images/cards_cropped/44968687.jpg"
          }
        ]
      },
      {
        "id": 94634433,
        "name": "Urgent Tuning",
        "card_images": [
          {
            "id": 94634433,
            "image_url": "https://images.ygoprodeck.com/images/cards/94634433.jpg",
            "image_url_small": "https://images.ygoprodeck.com/images/cards_small/94634433.jpg",
            "image_url_cropped": "https://images.ygoprodeck.com/images/cards_cropped/94634433.jpg"
          },
          {
            "id": 94634433,
            "image_url": "https://images.ygoprodeck.com/images/cards/94634433.jpg",
            "image_url_small": "https://images.ygoprodeck.com/images/cards_small/94634433.jpg",
            "image_url_cropped": "https://images.ygoprodeck.com/images/cards_cropped/94634433.jpg"
          }
        ]
      },
      {
        "id": 71692913,
        "name": "Xiangke Magician",
        "card_images": [
          {
            "id": 71692913,
            "image_url": "https://images.ygoprodeck.com/images/cards/71692913.jpg",
            "image_url_small": "https://images.ygoprodeck.com/images/cards_small/71692913.jpg",
            "image_url_cropped": "https://images.ygoprodeck.com/images/cards_cropped/71692913.jpg"
          },
          {
            "id": 71692913,
            "image_url": "https://images.ygoprodeck.com/images/cards/71692913.jpg",
            "image_url_small": "https://images.ygoprodeck.com/images/cards_small/71692913.jpg",
            "image_url_cropped": "https://images.ygoprodeck.com/images/cards_cropped/71692913.jpg"
          }
        ]
      },
      {
        "id": 17086528,
        "name": "Xiangsheng Magician",
        "card_images": [
          {
            "id": 17086528,
            "image_url": "https://images.ygoprodeck.com/images/cards/17086528.jpg",
            "image_url_small": "https://images.ygoprodeck.com/images/cards_small/17086528.jpg",
            "image_url_cropped": "https://images.ygoprodeck.com/images/cards_cropped/17086528.jpg"
          },
          {
            "id": 17086528,
            "image_url": "https://images.ygoprodeck.com/images/cards/17086528.jpg",
            "image_url_small": "https://images.ygoprodeck.com/images/cards_small/17086528.jpg",
            "image_url_cropped": "https://images.ygoprodeck.com/images/cards_cropped/17086528.jpg"
          }
        ]
      },
      {
        "id": 65247798,
        "name": "Yosenju Kama 1",
        "card_images": [
          {
            "id": 65247798,
            "image_url": "https://images.ygoprodeck.com/images/cards/65247798.jpg",
            "image_url_small": "https://images.ygoprodeck.com/images/cards_small/65247798.jpg",
            "image_url_cropped": "https://images.ygoprodeck.com/images/cards_cropped/65247798.jpg"
          },
          {
            "id": 65247798,
            "image_url": "https://images.ygoprodeck.com/images/cards/65247798.jpg",
            "image_url_small": "https://images.ygoprodeck.com/images/cards_small/65247798.jpg",
            "image_url_cropped": "https://images.ygoprodeck.com/images/cards_cropped/65247798.jpg"
          }
        ]
      },
      {
        "id": 92246806,
        "name": "Yosenju Kama 2",
        "card_images": [
          {
            "id": 92246806,
            "image_url": "https://images.ygoprodeck.com/images/cards/92246806.jpg",
            "image_url_small": "https://images.ygoprodeck.com/images/cards_small/92246806.jpg",
            "image_url_cropped": "https://images.ygoprodeck.com/images/cards_cropped/92246806.jpg"
          },
          {
            "id": 92246806,
            "image_url": "https://images.ygoprodeck.com/images/cards/92246806.jpg",
            "image_url_small": "https://images.ygoprodeck.com/images/cards_small/92246806.jpg",
            "image_url_cropped": "https://images.ygoprodeck.com/images/cards_cropped/92246806.jpg"
          }
        ]
      },
      {
        "id": 28630501,
        "name": "Yosenju Kama 3",
        "card_images": [
          {
            "id": 28630501,
            "image_url": "https://images.ygoprodeck.com/images/cards/28630501.jpg",
            "image_url_small": "https://images.ygoprodeck.com/images/cards_small/28630501.jpg",
            "image_url_cropped": "https://images.ygoprodeck.com/images/cards_cropped/28630501.jpg"
          },
          {
            "id": 28630501,
            "image_url": "https://images.ygoprodeck.com/images/cards/28630501.jpg",
            "image_url_small": "https://images.ygoprodeck.com/images/cards_small/28630501.jpg",
            "image_url_cropped": "https://images.ygoprodeck.com/images/cards_cropped/28630501.jpg"
          }
        ]
      },
      {
        "id": 65025250,
        "name": "Yosenju Shinchu L",
        "card_images": [
          {
            "id": 65025250,
            "image_url": "https://images.ygoprodeck.com/images/cards/65025250.jpg",
            "image_url_small": "https://images.ygoprodeck.com/images/cards_small/65025250.jpg",
            "image_url_cropped": "https://images.ygoprodeck.com/images/cards_cropped/65025250.jpg"
          },
          {
            "id": 65025250,
            "image_url": "https://images.ygoprodeck.com/images/cards/65025250.jpg",
            "image_url_small": "https://images.ygoprodeck.com/images/cards_small/65025250.jpg",
            "image_url_cropped": "https://images.ygoprodeck.com/images/cards_cropped/65025250.jpg"
          }
        ]
      },
      {
        "id": 91420254,
        "name": "Yosenju Shinchu R",
        "card_images": [
          {
            "id": 91420254,
            "image_url": "https://images.ygoprodeck.com/images/cards/91420254.jpg",
            "image_url_small": "https://images.ygoprodeck.com/images/cards_small/91420254.jpg",
            "image_url_cropped": "https://images.ygoprodeck.com/images/cards_cropped/91420254.jpg"
          },
          {
            "id": 91420254,
            "image_url": "https://images.ygoprodeck.com/images/cards/91420254.jpg",
            "image_url_small": "https://images.ygoprodeck.com/images/cards_small/91420254.jpg",
            "image_url_cropped": "https://images.ygoprodeck.com/images/cards_cropped/91420254.jpg"
          }
        ]
      },
      {
        "id": 54903668,
        "name": "Yosenjus' Secret Move",
        "card_images": [
          {
            "id": 54903668,
            "image_url": "https://images.ygoprodeck.com/images/cards/54903668.jpg",
            "image_url_small": "https://images.ygoprodeck.com/images/cards_small/54903668.jpg",
            "image_url_cropped": "https://images.ygoprodeck.com/images/cards_cropped/54903668.jpg"
          },
          {
            "id": 54903668,
            "image_url": "https://images.ygoprodeck.com/images/cards/54903668.jpg",
            "image_url_small": "https://images.ygoprodeck.com/images/cards_small/54903668.jpg",
            "image_url_cropped": "https://images.ygoprodeck.com/images/cards_cropped/54903668.jpg"
          }
        ]
      }
    ]
  }
}