{
  "setName": "The Lost Art Promotion A",
  "rarities": {
    "secret": [],
    "ultra": [
      {
        "id": 83764718,
        "name": "Monster Reborn",
        "card_images": [
          {
            "id": 83764718,
            "image_url": "https://images.ygoprodeck.com/images/cards/83764718.jpg",
            "image_url_small": "https://images.ygoprodeck.com/images/cards_small/83764718.jpg",
            "image_url_cropped": "https://images.ygoprodeck.com/images/cards_cropped/83764718.jpg"
          },
          {
            "id": 83764719,
            "image_url": "https://images.ygoprodeck.com/images/cards/83764719.jpg",
            "image_url_small": "https://images.ygoprodeck.com/images/cards_small/83764719.jpg",
            "image_url_cropped": "https://images.ygoprodeck.com/images/cards_cropped/83764719.jpg"
          }
        ]
      }
    ],
    "super": [],
    "rare": [],
    "common": []
  }
}